baseten_performance_client/__init__.py
baseten_performance_client/__init__.pyi
baseten_performance_client/baseten_performance_client.cpython-313t-aarch64-linux-musl.so
baseten_performance_client/py.typed
baseten_performance_client-0.1.5.dist-info/METADATA
baseten_performance_client-0.1.5.dist-info/WHEEL
baseten_performance_client.libs/libgcc_s-0bf60adc.so.1
baseten_performance_client-0.1.5.dist-info/RECORD
