Metadata-Version: 2.4
Name: baseten_performance_client
Version: 0.1.5
Classifier: Programming Language :: Rust
Classifier: Programming Language :: Python :: Implementation :: CPython
Classifier: Programming Language :: Python :: Implementation :: PyPy
Requires-Dist: requests
Summary: A ultra-high performance package for sending requests to Baseten Embedding Inference'
Author-email: Michael Feil <no-reply@baseten.co>
License-Expression: MIT
Requires-Python: >=3.8
Project-URL: Issues, https://github.com/basetenlabs/truss/issues
Project-URL: Repository, https://github.com/basetenlabs/truss.git
